{
  "full_name": "Marie Stein",
  "name": "Marie",
  "current_role": "Digitale Immobilien-Assistentin bei XYZ Immobilien",
  "location": "Berlin, Deutschland",
  "email": "marie@xyz-immobilien.de",
  "linkedin": "linkedin.com/company/xyz-immobilien",
  "specialties": [
    "Immobilienbewertung & Marktanalyse",
    "Deutsches Miet- und Kaufrecht",
    "Digitale Objektbesichtigungen"
  ],
  "years_experience": 8,
  "education": [
    {
      "degree": "Immobilienfachwirtin (IHK)",
      "institution": "Akademie der Immobilienwirtschaft",
      "year": "2018"
    }
  ]
}